README.rst
setup.py
django_mail_tester/__init__.py
django_mail_tester.egg-info/PKG-INFO
django_mail_tester.egg-info/SOURCES.txt
django_mail_tester.egg-info/dependency_links.txt
django_mail_tester.egg-info/not-zip-safe
django_mail_tester.egg-info/top_level.txt
django_mail_tester/management/__init__.py
django_mail_tester/management/commands/__init__.py
django_mail_tester/management/commands/sendmail.py