Metadata-Version: 1.1
Name: django-mail-tester
Version: 0.0.1
Summary: Django management command to send email
Home-page: https://github.com/satyrius/django-mail-tester
Author: Anton Egorov
Author-email: anton.egoroff@gmail.com
License: MIT
Platform: OS Independent
Classifier: Development Status :: 1 - Planning
Classifier: Environment :: Web Environment
Classifier: Framework :: Django
Classifier: Intended Audience :: Developers
Classifier: License :: OSI Approved :: MIT License
Classifier: Operating System :: OS Independent
Classifier: Programming Language :: Python :: 2.7
Classifier: Programming Language :: Python
Classifier: Topic :: Communications :: Email
Classifier: Topic :: Communications
Classifier: Topic :: Software Development :: Testing
Classifier: Topic :: Utilities
